xlwinxx/__init__.py
xlwinxx/xlwinxx.py
xlwinxx-0.1.dist-info/METADATA
xlwinxx-0.1.dist-info/WHEEL
xlwinxx-0.1.dist-info/top_level.txt
xlwinxx-0.1.dist-info/RECORD
