Metadata-Version: 2.1
Name: xlwinxx
Version: 0.1
Summary: xlwinxx
Author-email: applepro285@gmail.com
